zathenatos3/__init__.py
zathenatos3/athenatos3.py
zathenatos3-0.0.1.dist-info/LICENSE
zathenatos3-0.0.1.dist-info/METADATA
zathenatos3-0.0.1.dist-info/WHEEL
zathenatos3-0.0.1.dist-info/top_level.txt
zathenatos3-0.0.1.dist-info/RECORD
