Metadata-Version: 2.1
Name: zathenatos3
Version: 0.0.1
Summary: A simple package to flow data from athena to s3
Home-page: https://github.com/zyleu/athenatos3
Author: Zhiyi Leu
Author-email: leuzhiyi@gmai.com
License: UNKNOWN
Platform: UNKNOWN
Classifier: Programming Language :: Python :: 3
Classifier: License :: OSI Approved :: MIT License
Classifier: Operating System :: OS Independent
Requires-Python: >=3.6
License-File: LICENSE
